openmcp/__init__.py
openmcp/example.py
openmcp/test_search_text.py
openmcp/backends/__init__.py
openmcp/backends/base_provider.py
openmcp/backends/search_backend.py
openmcp/backends/vanilla_backend.py
openmcp/core/__init__.py
openmcp/core/widget.py
openmcp_cli/__init__.py
mcp_core-0.2.5.dist-info/METADATA
mcp_core-0.2.5.dist-info/WHEEL
mcp_core-0.2.5.dist-info/entry_points.txt
mcp_core-0.2.5.dist-info/top_level.txt
mcp_core-0.2.5.dist-info/RECORD
