Metadata-Version: 2.4
Name: mcp-core
Version: 0.2.5
Summary: Deploy MCP servers in seconds
Requires-Python: >=3.10
Requires-Dist: mcp>=1.0.0
Requires-Dist: httpx>=0.25.0
Provides-Extra: all
Requires-Dist: sentence-transformers>=2.0.0; extra == "all"
Requires-Dist: numpy>=1.24.0; extra == "all"
